<?xml version="1.0" encoding="UTF-8"?>
<ti:app xmlns:ti="http://ti.appcelerator.org">
    <property name="acs-oauth-secret-production" type="string">oeGihRH6H9Yo8mCFfBc3ThcEe3CN2mbl</property>
    <property name="acs-oauth-key-production" type="string">oO305EzAyPU04nwwed5XFp7URtcXlSUK</property>
    <property name="acs-api-key-production" type="string">0htZHgMQvWXPoAjnPzLJUh0IEiqvH24A</property>
    <property name="acs-oauth-secret-development" type="string">tFKgPyfPa97cc3jnvEncmzJYxYpCn8Gw</property>
    <property name="acs-oauth-key-development" type="string">xsTrPnfczLMZSoz8V6hOdzbHEdGYG78O</property>
    <property name="acs-api-key-development" type="string">b3WLjGXZiK73tfwhMCV0rtPNV3kvWhrm</property>
    <id>com.hippocreative.WDMSlingCalculatorApp</id>
    <name>WHC Sling Calculator</name>
    <version>1.0.6</version>
    <publisher>Hippo Marketing</publisher>
    <url>http://www.hippocreative.com</url>
    <description>Configure your Chain / Wire rope sling and receive an instant quotation.</description>
    <copyright>William Hackett Chains Ltd</copyright>
    <icon>appicon.png</icon>
    <statusbar-style>light_content</statusbar-style>
    <fullscreen>false</fullscreen>
    <navbar-hidden>false</navbar-hidden>
    <analytics>true</analytics>
    <guid>124ea914-475f-4251-9555-48b7d9ef039f</guid>
    <property name="ti.ui.defaultunit" type="string">dp</property>
    <ios>
        <plist>
            <dict>
                <key>UISupportedInterfaceOrientations~iphone</key>
                <array>
                    <string>UIInterfaceOrientationPortrait</string>
                </array>
                <key>UISupportedInterfaceOrientations~ipad</key>
                <array>
                    <string>UIInterfaceOrientationPortrait</string>
                    <string>UIInterfaceOrientationPortraitUpsideDown</string>
                    <string>UIInterfaceOrientationLandscapeLeft</string>
                    <string>UIInterfaceOrientationLandscapeRight</string>
                </array>
                <key>UIRequiresPersistentWiFi</key>
                <false/>
                <key>UIPrerenderedIcon</key>
                <false/>
                <key>UIStatusBarHidden</key>
                <false/>
                <key>UIStatusBarStyle</key>
                <string>UIStatusBarStyleDefault</string>
            </dict>
        </plist>
    </ios>
    <android xmlns:android="http://schemas.android.com/apk/res/android">
        <manifest android:versionCode="5" android:versionName="1.0.6">
            <application>
                <activity
                    android:configChanges="keyboardHidden|orientation"
                    android:name="org.appcelerator.titanium.TiActivity" android:screenOrientation="portrait"/>
                <activity
                    android:configChanges="keyboardHidden|orientation"
                    android:name="org.appcelerator.titanium.TiTranslucentActivity"
                    android:screenOrientation="portrait" android:theme="@style/Theme.AppCompat.Light"/>
                <activity
                    android:configChanges="keyboardHidden|orientation"
                    android:name="org.appcelerator.titanium.TiModalActivity"
                    android:screenOrientation="portrait" android:theme="@style/Theme.AppCompat.Light"/>
                <activity
                    android:configChanges="keyboardHidden|orientation"
                    android:name="ti.modules.titanium.ui.TiTabActivity" android:screenOrientation="portrait"/>
                <activity
                    android:name="ti.modules.titanium.ui.android.TiPreferencesActivity" android:screenOrientation="portrait"/>
            </application>
        </manifest>
    </android>
    <mobileweb>
        <precache/>
        <splash>
            <enabled>true</enabled>
            <inline-css-images>true</inline-css-images>
        </splash>
        <theme>default</theme>
    </mobileweb>
    <modules/>
    <deployment-targets>
        <target device="android">true</target>
        <target device="ipad">true</target>
        <target device="iphone">true</target>
        <target device="mobileweb">false</target>
    </deployment-targets>
    <sdk-version>5.1.2.GA</sdk-version>
    <plugins>
        <plugin version="1.0">ti.alloy</plugin>
    </plugins>
    <property name="appc-app-id" type="string">56aa179fd3d420bb46c2406e</property>
    <property name="acs-authbase-url-development" type="string">https://secure-identity.cloud.appcelerator.com</property>
    <property name="acs-base-url-development" type="string">https://api.cloud.appcelerator.com</property>
    <property name="acs-username-development" type="string">appc_app_user_dev</property>
    <property name="acs-password-development" type="string">gBHEAPsYusZgM4qzGo</property>
    <property name="acs-authbase-url-production" type="string">https://secure-identity.cloud.appcelerator.com</property>
    <property name="acs-base-url-production" type="string">https://api.cloud.appcelerator.com</property>
    <property name="acs-username-production" type="string">appc_app_user</property>
    <property name="acs-password-production" type="string">5GKoBSTuOj9kqy6AWI</property>
    <property name="appc-org-id" type="string">100038912</property>
    <property name="appc-creator-user-id" type="string">6eb43250-3fca-40f0-a32c-690217b7c952</property>
</ti:app>
